{
  "id": "cb332a38-574d-47da-ad4e-b906efab5af8",
  "prevId": "00000000-0000-0000-0000-000000000000",
  "version": "7",
  "dialect": "postgresql",
  "tables": {
    "public.audit_logs": {
      "name": "audit_logs",
      "schema": "",
      "columns": {
        "id": {
          "name": "id",
          "type": "uuid",
          "primaryKey": true,
          "notNull": true,
          "default": "uuidv7()"
        },
        "user_id": {
          "name": "user_id",
          "type": "uuid",
          "primaryKey": false,
          "notNull": false
        },
        "oauth_client_id": {
          "name": "oauth_client_id",
          "type": "uuid",
          "primaryKey": false,
          "notNull": false
        },
        "event": {
          "name": "event",
          "type": "varchar(100)",
          "primaryKey": false,
          "notNull": true
        },
        "event_type": {
          "name": "event_type",
          "type": "audit_event_type",
          "typeSchema": "public",
          "primaryKey": false,
          "notNull": true
        },
        "success": {
          "name": "success",
          "type": "boolean",
          "primaryKey": false,
          "notNull": true,
          "default": true
        },
        "ip_address": {
          "name": "ip_address",
          "type": "varchar(45)",
          "primaryKey": false,
          "notNull": false
        },
        "user_agent": {
          "name": "user_agent",
          "type": "text",
          "primaryKey": false,
          "notNull": false
        },
        "metadata": {
          "name": "metadata",
          "type": "jsonb",
          "primaryKey": false,
          "notNull": false
        },
        "created_at": {
          "name": "created_at",
          "type": "bigint",
          "primaryKey": false,
          "notNull": true,
          "default": "(EXTRACT(EPOCH FROM NOW())::bigint * 1000)"
        }
      },
      "indexes": {
        "idx_audit_logs_user_id": {
          "name": "idx_audit_logs_user_id",
          "columns": [
            {
              "expression": "user_id",
              "isExpression": false,
              "asc": true,
              "nulls": "last"
            }
          ],
          "isUnique": false,
          "concurrently": false,
          "method": "btree",
          "with": {}
        },
        "idx_audit_logs_oauth_client_id": {
          "name": "idx_audit_logs_oauth_client_id",
          "columns": [
            {
              "expression": "oauth_client_id",
              "isExpression": false,
              "asc": true,
              "nulls": "last"
            }
          ],
          "isUnique": false,
          "concurrently": false,
          "method": "btree",
          "with": {}
        },
        "idx_audit_logs_event_type": {
          "name": "idx_audit_logs_event_type",
          "columns": [
            {
              "expression": "event_type",
              "isExpression": false,
              "asc": true,
              "nulls": "last"
            }
          ],
          "isUnique": false,
          "concurrently": false,
          "method": "btree",
          "with": {}
        },
        "idx_audit_logs_event": {
          "name": "idx_audit_logs_event",
          "columns": [
            {
              "expression": "event",
              "isExpression": false,
              "asc": true,
              "nulls": "last"
            }
          ],
          "isUnique": false,
          "concurrently": false,
          "method": "btree",
          "with": {}
        },
        "idx_audit_logs_created_at": {
          "name": "idx_audit_logs_created_at",
          "columns": [
            {
              "expression": "created_at",
              "isExpression": false,
              "asc": true,
              "nulls": "last"
            }
          ],
          "isUnique": false,
          "concurrently": false,
          "method": "btree",
          "with": {}
        },
        "idx_audit_logs_user_event": {
          "name": "idx_audit_logs_user_event",
          "columns": [
            {
              "expression": "user_id",
              "isExpression": false,
              "asc": true,
              "nulls": "last"
            },
            {
              "expression": "event",
              "isExpression": false,
              "asc": true,
              "nulls": "last"
            },
            {
              "expression": "created_at",
              "isExpression": false,
              "asc": true,
              "nulls": "last"
            }
          ],
          "isUnique": false,
          "concurrently": false,
          "method": "btree",
          "with": {}
        },
        "idx_audit_logs_failed": {
          "name": "idx_audit_logs_failed",
          "columns": [
            {
              "expression": "event",
              "isExpression": false,
              "asc": true,
              "nulls": "last"
            },
            {
              "expression": "created_at",
              "isExpression": false,
              "asc": true,
              "nulls": "last"
            }
          ],
          "isUnique": false,
          "where": "\"audit_logs\".\"success\" = false",
          "concurrently": false,
          "method": "btree",
          "with": {}
        },
        "idx_audit_logs_ip_address": {
          "name": "idx_audit_logs_ip_address",
          "columns": [
            {
              "expression": "ip_address",
              "isExpression": false,
              "asc": true,
              "nulls": "last"
            }
          ],
          "isUnique": false,
          "concurrently": false,
          "method": "btree",
          "with": {}
        }
      },
      "foreignKeys": {
        "audit_logs_user_id_users_id_fk": {
          "name": "audit_logs_user_id_users_id_fk",
          "tableFrom": "audit_logs",
          "tableTo": "users",
          "columnsFrom": ["user_id"],
          "columnsTo": ["id"],
          "onDelete": "set null",
          "onUpdate": "no action"
        },
        "audit_logs_oauth_client_id_oauth_clients_id_fk": {
          "name": "audit_logs_oauth_client_id_oauth_clients_id_fk",
          "tableFrom": "audit_logs",
          "tableTo": "oauth_clients",
          "columnsFrom": ["oauth_client_id"],
          "columnsTo": ["id"],
          "onDelete": "set null",
          "onUpdate": "no action"
        }
      },
      "compositePrimaryKeys": {},
      "uniqueConstraints": {},
      "policies": {},
      "checkConstraints": {},
      "isRLSEnabled": false
    },
    "public.oauth_clients": {
      "name": "oauth_clients",
      "schema": "",
      "columns": {
        "id": {
          "name": "id",
          "type": "uuid",
          "primaryKey": true,
          "notNull": true,
          "default": "uuidv7()"
        },
        "realm_id": {
          "name": "realm_id",
          "type": "uuid",
          "primaryKey": false,
          "notNull": true
        },
        "client_id": {
          "name": "client_id",
          "type": "varchar(255)",
          "primaryKey": false,
          "notNull": true
        },
        "client_secret_hash": {
          "name": "client_secret_hash",
          "type": "text",
          "primaryKey": false,
          "notNull": true
        },
        "name": {
          "name": "name",
          "type": "varchar(255)",
          "primaryKey": false,
          "notNull": true
        },
        "description": {
          "name": "description",
          "type": "text",
          "primaryKey": false,
          "notNull": false
        },
        "redirect_uris": {
          "name": "redirect_uris",
          "type": "jsonb",
          "primaryKey": false,
          "notNull": true
        },
        "scopes": {
          "name": "scopes",
          "type": "jsonb",
          "primaryKey": false,
          "notNull": true,
          "default": "'[]'::jsonb"
        },
        "enabled": {
          "name": "enabled",
          "type": "boolean",
          "primaryKey": false,
          "notNull": true,
          "default": true
        },
        "require_pkce": {
          "name": "require_pkce",
          "type": "boolean",
          "primaryKey": false,
          "notNull": true,
          "default": true
        },
        "token_endpoint_auth_method": {
          "name": "token_endpoint_auth_method",
          "type": "token_endpoint_auth_method",
          "typeSchema": "public",
          "primaryKey": false,
          "notNull": true,
          "default": "'client_secret_post'"
        },
        "grant_types": {
          "name": "grant_types",
          "type": "jsonb",
          "primaryKey": false,
          "notNull": true,
          "default": "'[\"authorization_code\",\"refresh_token\"]'::jsonb"
        },
        "response_types": {
          "name": "response_types",
          "type": "jsonb",
          "primaryKey": false,
          "notNull": true,
          "default": "'[\"code\"]'::jsonb"
        },
        "developer_id": {
          "name": "developer_id",
          "type": "uuid",
          "primaryKey": false,
          "notNull": false
        },
        "metadata": {
          "name": "metadata",
          "type": "jsonb",
          "primaryKey": false,
          "notNull": false
        },
        "created_at": {
          "name": "created_at",
          "type": "bigint",
          "primaryKey": false,
          "notNull": true,
          "default": "(EXTRACT(EPOCH FROM NOW())::bigint * 1000)"
        },
        "updated_at": {
          "name": "updated_at",
          "type": "bigint",
          "primaryKey": false,
          "notNull": true,
          "default": "(EXTRACT(EPOCH FROM NOW())::bigint * 1000)"
        },
        "last_used_at": {
          "name": "last_used_at",
          "type": "bigint",
          "primaryKey": false,
          "notNull": false
        }
      },
      "indexes": {
        "idx_oauth_clients_realm_client_id_unique": {
          "name": "idx_oauth_clients_realm_client_id_unique",
          "columns": [
            {
              "expression": "realm_id",
              "isExpression": false,
              "asc": true,
              "nulls": "last"
            },
            {
              "expression": "client_id",
              "isExpression": false,
              "asc": true,
              "nulls": "last"
            }
          ],
          "isUnique": true,
          "concurrently": false,
          "method": "btree",
          "with": {}
        },
        "idx_oauth_clients_client_id": {
          "name": "idx_oauth_clients_client_id",
          "columns": [
            {
              "expression": "client_id",
              "isExpression": false,
              "asc": true,
              "nulls": "last"
            }
          ],
          "isUnique": false,
          "concurrently": false,
          "method": "btree",
          "with": {}
        },
        "idx_oauth_clients_realm_id": {
          "name": "idx_oauth_clients_realm_id",
          "columns": [
            {
              "expression": "realm_id",
              "isExpression": false,
              "asc": true,
              "nulls": "last"
            }
          ],
          "isUnique": false,
          "concurrently": false,
          "method": "btree",
          "with": {}
        },
        "idx_oauth_clients_developer_id": {
          "name": "idx_oauth_clients_developer_id",
          "columns": [
            {
              "expression": "developer_id",
              "isExpression": false,
              "asc": true,
              "nulls": "last"
            }
          ],
          "isUnique": false,
          "concurrently": false,
          "method": "btree",
          "with": {}
        },
        "idx_oauth_clients_enabled": {
          "name": "idx_oauth_clients_enabled",
          "columns": [
            {
              "expression": "enabled",
              "isExpression": false,
              "asc": true,
              "nulls": "last"
            }
          ],
          "isUnique": false,
          "where": "\"oauth_clients\".\"enabled\" = true",
          "concurrently": false,
          "method": "btree",
          "with": {}
        },
        "idx_oauth_clients_realm_client_id_enabled": {
          "name": "idx_oauth_clients_realm_client_id_enabled",
          "columns": [
            {
              "expression": "realm_id",
              "isExpression": false,
              "asc": true,
              "nulls": "last"
            },
            {
              "expression": "client_id",
              "isExpression": false,
              "asc": true,
              "nulls": "last"
            },
            {
              "expression": "enabled",
              "isExpression": false,
              "asc": true,
              "nulls": "last"
            }
          ],
          "isUnique": false,
          "concurrently": false,
          "method": "btree",
          "with": {}
        }
      },
      "foreignKeys": {
        "oauth_clients_realm_id_realms_id_fk": {
          "name": "oauth_clients_realm_id_realms_id_fk",
          "tableFrom": "oauth_clients",
          "tableTo": "realms",
          "columnsFrom": ["realm_id"],
          "columnsTo": ["id"],
          "onDelete": "cascade",
          "onUpdate": "no action"
        },
        "oauth_clients_developer_id_users_id_fk": {
          "name": "oauth_clients_developer_id_users_id_fk",
          "tableFrom": "oauth_clients",
          "tableTo": "users",
          "columnsFrom": ["developer_id"],
          "columnsTo": ["id"],
          "onDelete": "set null",
          "onUpdate": "no action"
        }
      },
      "compositePrimaryKeys": {},
      "uniqueConstraints": {},
      "policies": {},
      "checkConstraints": {},
      "isRLSEnabled": false
    },
    "public.realms": {
      "name": "realms",
      "schema": "",
      "columns": {
        "id": {
          "name": "id",
          "type": "uuid",
          "primaryKey": true,
          "notNull": true,
          "default": "uuidv7()"
        },
        "name": {
          "name": "name",
          "type": "varchar(255)",
          "primaryKey": false,
          "notNull": true
        },
        "enabled": {
          "name": "enabled",
          "type": "boolean",
          "primaryKey": false,
          "notNull": true,
          "default": true
        },
        "access_token_lifespan": {
          "name": "access_token_lifespan",
          "type": "bigint",
          "primaryKey": false,
          "notNull": false,
          "default": 900
        },
        "refresh_token_lifespan": {
          "name": "refresh_token_lifespan",
          "type": "bigint",
          "primaryKey": false,
          "notNull": false,
          "default": 604800
        },
        "ssl_required": {
          "name": "ssl_required",
          "type": "ssl_required",
          "typeSchema": "public",
          "primaryKey": false,
          "notNull": false,
          "default": "'external'"
        },
        "verify_email": {
          "name": "verify_email",
          "type": "boolean",
          "primaryKey": false,
          "notNull": true,
          "default": true
        },
        "registration_allowed": {
          "name": "registration_allowed",
          "type": "boolean",
          "primaryKey": false,
          "notNull": true,
          "default": false
        },
        "login_with_email_allowed": {
          "name": "login_with_email_allowed",
          "type": "boolean",
          "primaryKey": false,
          "notNull": true,
          "default": true
        },
        "duplicate_emails_allowed": {
          "name": "duplicate_emails_allowed",
          "type": "boolean",
          "primaryKey": false,
          "notNull": true,
          "default": false
        },
        "password_policy": {
          "name": "password_policy",
          "type": "jsonb",
          "primaryKey": false,
          "notNull": false
        },
        "sso_idle_timeout": {
          "name": "sso_idle_timeout",
          "type": "bigint",
          "primaryKey": false,
          "notNull": false
        },
        "sso_max_lifespan": {
          "name": "sso_max_lifespan",
          "type": "bigint",
          "primaryKey": false,
          "notNull": false
        },
        "revoke_refresh_token": {
          "name": "revoke_refresh_token",
          "type": "boolean",
          "primaryKey": false,
          "notNull": true,
          "default": false
        },
        "refresh_token_max_reuse": {
          "name": "refresh_token_max_reuse",
          "type": "bigint",
          "primaryKey": false,
          "notNull": false,
          "default": 0
        },
        "default_locale": {
          "name": "default_locale",
          "type": "varchar(10)",
          "primaryKey": false,
          "notNull": false
        },
        "supported_locales": {
          "name": "supported_locales",
          "type": "jsonb",
          "primaryKey": false,
          "notNull": false,
          "default": "'[]'::jsonb"
        },
        "metadata": {
          "name": "metadata",
          "type": "jsonb",
          "primaryKey": false,
          "notNull": false
        },
        "created_at": {
          "name": "created_at",
          "type": "bigint",
          "primaryKey": false,
          "notNull": true,
          "default": "(EXTRACT(EPOCH FROM NOW())::bigint * 1000)"
        },
        "updated_at": {
          "name": "updated_at",
          "type": "bigint",
          "primaryKey": false,
          "notNull": true,
          "default": "(EXTRACT(EPOCH FROM NOW())::bigint * 1000)"
        }
      },
      "indexes": {
        "idx_realms_enabled": {
          "name": "idx_realms_enabled",
          "columns": [
            {
              "expression": "enabled",
              "isExpression": false,
              "asc": true,
              "nulls": "last"
            }
          ],
          "isUnique": false,
          "where": "\"realms\".\"enabled\" = true",
          "concurrently": false,
          "method": "btree",
          "with": {}
        }
      },
      "foreignKeys": {},
      "compositePrimaryKeys": {},
      "uniqueConstraints": {
        "realms_name_unique": {
          "name": "realms_name_unique",
          "nullsNotDistinct": false,
          "columns": ["name"]
        }
      },
      "policies": {},
      "checkConstraints": {},
      "isRLSEnabled": false
    },
    "public.users": {
      "name": "users",
      "schema": "",
      "columns": {
        "id": {
          "name": "id",
          "type": "uuid",
          "primaryKey": true,
          "notNull": true,
          "default": "uuidv7()"
        },
        "realm_id": {
          "name": "realm_id",
          "type": "uuid",
          "primaryKey": false,
          "notNull": true
        },
        "email": {
          "name": "email",
          "type": "varchar(255)",
          "primaryKey": false,
          "notNull": true
        },
        "email_normalized": {
          "name": "email_normalized",
          "type": "varchar(255)",
          "primaryKey": false,
          "notNull": true
        },
        "password_hash": {
          "name": "password_hash",
          "type": "text",
          "primaryKey": false,
          "notNull": true
        },
        "email_verified": {
          "name": "email_verified",
          "type": "boolean",
          "primaryKey": false,
          "notNull": true,
          "default": false
        },
        "enabled": {
          "name": "enabled",
          "type": "boolean",
          "primaryKey": false,
          "notNull": true,
          "default": true
        },
        "first_name": {
          "name": "first_name",
          "type": "varchar(255)",
          "primaryKey": false,
          "notNull": false
        },
        "last_name": {
          "name": "last_name",
          "type": "varchar(255)",
          "primaryKey": false,
          "notNull": false
        },
        "metadata": {
          "name": "metadata",
          "type": "jsonb",
          "primaryKey": false,
          "notNull": false
        },
        "created_at": {
          "name": "created_at",
          "type": "bigint",
          "primaryKey": false,
          "notNull": true,
          "default": "(EXTRACT(EPOCH FROM NOW())::bigint * 1000)"
        },
        "updated_at": {
          "name": "updated_at",
          "type": "bigint",
          "primaryKey": false,
          "notNull": true,
          "default": "(EXTRACT(EPOCH FROM NOW())::bigint * 1000)"
        },
        "last_login_at": {
          "name": "last_login_at",
          "type": "bigint",
          "primaryKey": false,
          "notNull": false
        },
        "email_verified_at": {
          "name": "email_verified_at",
          "type": "bigint",
          "primaryKey": false,
          "notNull": false
        }
      },
      "indexes": {
        "idx_users_realm_email_normalized_unique": {
          "name": "idx_users_realm_email_normalized_unique",
          "columns": [
            {
              "expression": "realm_id",
              "isExpression": false,
              "asc": true,
              "nulls": "last"
            },
            {
              "expression": "email_normalized",
              "isExpression": false,
              "asc": true,
              "nulls": "last"
            }
          ],
          "isUnique": true,
          "concurrently": false,
          "method": "btree",
          "with": {}
        },
        "idx_users_email": {
          "name": "idx_users_email",
          "columns": [
            {
              "expression": "email",
              "isExpression": false,
              "asc": true,
              "nulls": "last"
            }
          ],
          "isUnique": false,
          "concurrently": false,
          "method": "btree",
          "with": {}
        },
        "idx_users_realm_id": {
          "name": "idx_users_realm_id",
          "columns": [
            {
              "expression": "realm_id",
              "isExpression": false,
              "asc": true,
              "nulls": "last"
            }
          ],
          "isUnique": false,
          "concurrently": false,
          "method": "btree",
          "with": {}
        },
        "idx_users_enabled": {
          "name": "idx_users_enabled",
          "columns": [
            {
              "expression": "enabled",
              "isExpression": false,
              "asc": true,
              "nulls": "last"
            }
          ],
          "isUnique": false,
          "where": "\"users\".\"enabled\" = true",
          "concurrently": false,
          "method": "btree",
          "with": {}
        },
        "idx_users_realm_email_enabled": {
          "name": "idx_users_realm_email_enabled",
          "columns": [
            {
              "expression": "realm_id",
              "isExpression": false,
              "asc": true,
              "nulls": "last"
            },
            {
              "expression": "email_normalized",
              "isExpression": false,
              "asc": true,
              "nulls": "last"
            },
            {
              "expression": "enabled",
              "isExpression": false,
              "asc": true,
              "nulls": "last"
            }
          ],
          "isUnique": false,
          "concurrently": false,
          "method": "btree",
          "with": {}
        }
      },
      "foreignKeys": {
        "users_realm_id_realms_id_fk": {
          "name": "users_realm_id_realms_id_fk",
          "tableFrom": "users",
          "tableTo": "realms",
          "columnsFrom": ["realm_id"],
          "columnsTo": ["id"],
          "onDelete": "cascade",
          "onUpdate": "no action"
        }
      },
      "compositePrimaryKeys": {},
      "uniqueConstraints": {},
      "policies": {},
      "checkConstraints": {},
      "isRLSEnabled": false
    },
    "public.roles": {
      "name": "roles",
      "schema": "",
      "columns": {
        "id": {
          "name": "id",
          "type": "uuid",
          "primaryKey": true,
          "notNull": true,
          "default": "uuidv7()"
        },
        "realm_id": {
          "name": "realm_id",
          "type": "uuid",
          "primaryKey": false,
          "notNull": true
        },
        "name": {
          "name": "name",
          "type": "varchar(255)",
          "primaryKey": false,
          "notNull": true
        },
        "description": {
          "name": "description",
          "type": "text",
          "primaryKey": false,
          "notNull": false
        },
        "oauth_client_id": {
          "name": "oauth_client_id",
          "type": "uuid",
          "primaryKey": false,
          "notNull": false
        },
        "enabled": {
          "name": "enabled",
          "type": "boolean",
          "primaryKey": false,
          "notNull": true,
          "default": true
        },
        "metadata": {
          "name": "metadata",
          "type": "jsonb",
          "primaryKey": false,
          "notNull": false
        },
        "created_at": {
          "name": "created_at",
          "type": "bigint",
          "primaryKey": false,
          "notNull": true,
          "default": "(EXTRACT(EPOCH FROM NOW())::bigint * 1000)"
        },
        "updated_at": {
          "name": "updated_at",
          "type": "bigint",
          "primaryKey": false,
          "notNull": true,
          "default": "(EXTRACT(EPOCH FROM NOW())::bigint * 1000)"
        }
      },
      "indexes": {
        "idx_roles_realm_name_unique": {
          "name": "idx_roles_realm_name_unique",
          "columns": [
            {
              "expression": "realm_id",
              "isExpression": false,
              "asc": true,
              "nulls": "last"
            },
            {
              "expression": "name",
              "isExpression": false,
              "asc": true,
              "nulls": "last"
            },
            {
              "expression": "oauth_client_id",
              "isExpression": false,
              "asc": true,
              "nulls": "last"
            }
          ],
          "isUnique": true,
          "concurrently": false,
          "method": "btree",
          "with": {}
        },
        "idx_roles_name": {
          "name": "idx_roles_name",
          "columns": [
            {
              "expression": "name",
              "isExpression": false,
              "asc": true,
              "nulls": "last"
            }
          ],
          "isUnique": false,
          "concurrently": false,
          "method": "btree",
          "with": {}
        },
        "idx_roles_realm_id": {
          "name": "idx_roles_realm_id",
          "columns": [
            {
              "expression": "realm_id",
              "isExpression": false,
              "asc": true,
              "nulls": "last"
            }
          ],
          "isUnique": false,
          "concurrently": false,
          "method": "btree",
          "with": {}
        },
        "idx_roles_oauth_client_id": {
          "name": "idx_roles_oauth_client_id",
          "columns": [
            {
              "expression": "oauth_client_id",
              "isExpression": false,
              "asc": true,
              "nulls": "last"
            }
          ],
          "isUnique": false,
          "concurrently": false,
          "method": "btree",
          "with": {}
        }
      },
      "foreignKeys": {
        "roles_realm_id_realms_id_fk": {
          "name": "roles_realm_id_realms_id_fk",
          "tableFrom": "roles",
          "tableTo": "realms",
          "columnsFrom": ["realm_id"],
          "columnsTo": ["id"],
          "onDelete": "cascade",
          "onUpdate": "no action"
        },
        "roles_oauth_client_id_oauth_clients_id_fk": {
          "name": "roles_oauth_client_id_oauth_clients_id_fk",
          "tableFrom": "roles",
          "tableTo": "oauth_clients",
          "columnsFrom": ["oauth_client_id"],
          "columnsTo": ["id"],
          "onDelete": "set null",
          "onUpdate": "no action"
        }
      },
      "compositePrimaryKeys": {},
      "uniqueConstraints": {},
      "policies": {},
      "checkConstraints": {},
      "isRLSEnabled": false
    },
    "public.user_roles": {
      "name": "user_roles",
      "schema": "",
      "columns": {
        "user_id": {
          "name": "user_id",
          "type": "uuid",
          "primaryKey": false,
          "notNull": true
        },
        "role_id": {
          "name": "role_id",
          "type": "uuid",
          "primaryKey": false,
          "notNull": true
        },
        "assigned_at": {
          "name": "assigned_at",
          "type": "bigint",
          "primaryKey": false,
          "notNull": true,
          "default": "(EXTRACT(EPOCH FROM NOW())::bigint * 1000)"
        },
        "assigned_by": {
          "name": "assigned_by",
          "type": "uuid",
          "primaryKey": false,
          "notNull": false
        }
      },
      "indexes": {
        "idx_user_roles_user_id": {
          "name": "idx_user_roles_user_id",
          "columns": [
            {
              "expression": "user_id",
              "isExpression": false,
              "asc": true,
              "nulls": "last"
            }
          ],
          "isUnique": false,
          "concurrently": false,
          "method": "btree",
          "with": {}
        },
        "idx_user_roles_role_id": {
          "name": "idx_user_roles_role_id",
          "columns": [
            {
              "expression": "role_id",
              "isExpression": false,
              "asc": true,
              "nulls": "last"
            }
          ],
          "isUnique": false,
          "concurrently": false,
          "method": "btree",
          "with": {}
        }
      },
      "foreignKeys": {
        "user_roles_user_id_users_id_fk": {
          "name": "user_roles_user_id_users_id_fk",
          "tableFrom": "user_roles",
          "tableTo": "users",
          "columnsFrom": ["user_id"],
          "columnsTo": ["id"],
          "onDelete": "cascade",
          "onUpdate": "no action"
        },
        "user_roles_role_id_roles_id_fk": {
          "name": "user_roles_role_id_roles_id_fk",
          "tableFrom": "user_roles",
          "tableTo": "roles",
          "columnsFrom": ["role_id"],
          "columnsTo": ["id"],
          "onDelete": "cascade",
          "onUpdate": "no action"
        },
        "user_roles_assigned_by_users_id_fk": {
          "name": "user_roles_assigned_by_users_id_fk",
          "tableFrom": "user_roles",
          "tableTo": "users",
          "columnsFrom": ["assigned_by"],
          "columnsTo": ["id"],
          "onDelete": "set null",
          "onUpdate": "no action"
        }
      },
      "compositePrimaryKeys": {
        "user_roles_pk": {
          "name": "user_roles_pk",
          "columns": ["user_id", "role_id"]
        }
      },
      "uniqueConstraints": {},
      "policies": {},
      "checkConstraints": {},
      "isRLSEnabled": false
    },
    "public.sessions": {
      "name": "sessions",
      "schema": "",
      "columns": {
        "id": {
          "name": "id",
          "type": "uuid",
          "primaryKey": true,
          "notNull": true,
          "default": "uuidv7()"
        },
        "user_id": {
          "name": "user_id",
          "type": "uuid",
          "primaryKey": false,
          "notNull": true
        },
        "oauth_client_id": {
          "name": "oauth_client_id",
          "type": "uuid",
          "primaryKey": false,
          "notNull": false
        },
        "access_token_hash": {
          "name": "access_token_hash",
          "type": "text",
          "primaryKey": false,
          "notNull": false
        },
        "refresh_token_hash": {
          "name": "refresh_token_hash",
          "type": "text",
          "primaryKey": false,
          "notNull": false
        },
        "ip_address": {
          "name": "ip_address",
          "type": "varchar(45)",
          "primaryKey": false,
          "notNull": false
        },
        "user_agent": {
          "name": "user_agent",
          "type": "text",
          "primaryKey": false,
          "notNull": false
        },
        "expires_at": {
          "name": "expires_at",
          "type": "bigint",
          "primaryKey": false,
          "notNull": true
        },
        "revoked": {
          "name": "revoked",
          "type": "boolean",
          "primaryKey": false,
          "notNull": true,
          "default": false
        },
        "revoked_at": {
          "name": "revoked_at",
          "type": "bigint",
          "primaryKey": false,
          "notNull": false
        },
        "created_at": {
          "name": "created_at",
          "type": "bigint",
          "primaryKey": false,
          "notNull": true,
          "default": "(EXTRACT(EPOCH FROM NOW())::bigint * 1000)"
        },
        "last_activity_at": {
          "name": "last_activity_at",
          "type": "bigint",
          "primaryKey": false,
          "notNull": true,
          "default": "(EXTRACT(EPOCH FROM NOW())::bigint * 1000)"
        }
      },
      "indexes": {
        "idx_sessions_user_id": {
          "name": "idx_sessions_user_id",
          "columns": [
            {
              "expression": "user_id",
              "isExpression": false,
              "asc": true,
              "nulls": "last"
            }
          ],
          "isUnique": false,
          "concurrently": false,
          "method": "btree",
          "with": {}
        },
        "idx_sessions_active": {
          "name": "idx_sessions_active",
          "columns": [
            {
              "expression": "user_id",
              "isExpression": false,
              "asc": true,
              "nulls": "last"
            },
            {
              "expression": "expires_at",
              "isExpression": false,
              "asc": true,
              "nulls": "last"
            }
          ],
          "isUnique": false,
          "where": "\"sessions\".\"revoked\" = false",
          "concurrently": false,
          "method": "btree",
          "with": {}
        },
        "idx_sessions_expires_at": {
          "name": "idx_sessions_expires_at",
          "columns": [
            {
              "expression": "expires_at",
              "isExpression": false,
              "asc": true,
              "nulls": "last"
            }
          ],
          "isUnique": false,
          "concurrently": false,
          "method": "btree",
          "with": {}
        },
        "idx_sessions_access_token_hash": {
          "name": "idx_sessions_access_token_hash",
          "columns": [
            {
              "expression": "access_token_hash",
              "isExpression": false,
              "asc": true,
              "nulls": "last"
            }
          ],
          "isUnique": false,
          "concurrently": false,
          "method": "btree",
          "with": {}
        },
        "idx_sessions_oauth_client_id": {
          "name": "idx_sessions_oauth_client_id",
          "columns": [
            {
              "expression": "oauth_client_id",
              "isExpression": false,
              "asc": true,
              "nulls": "last"
            }
          ],
          "isUnique": false,
          "concurrently": false,
          "method": "btree",
          "with": {}
        }
      },
      "foreignKeys": {
        "sessions_user_id_users_id_fk": {
          "name": "sessions_user_id_users_id_fk",
          "tableFrom": "sessions",
          "tableTo": "users",
          "columnsFrom": ["user_id"],
          "columnsTo": ["id"],
          "onDelete": "cascade",
          "onUpdate": "no action"
        },
        "sessions_oauth_client_id_oauth_clients_id_fk": {
          "name": "sessions_oauth_client_id_oauth_clients_id_fk",
          "tableFrom": "sessions",
          "tableTo": "oauth_clients",
          "columnsFrom": ["oauth_client_id"],
          "columnsTo": ["id"],
          "onDelete": "set null",
          "onUpdate": "no action"
        }
      },
      "compositePrimaryKeys": {},
      "uniqueConstraints": {},
      "policies": {},
      "checkConstraints": {},
      "isRLSEnabled": false
    },
    "public.authorization_codes": {
      "name": "authorization_codes",
      "schema": "",
      "columns": {
        "id": {
          "name": "id",
          "type": "uuid",
          "primaryKey": true,
          "notNull": true,
          "default": "uuidv7()"
        },
        "code": {
          "name": "code",
          "type": "varchar(255)",
          "primaryKey": false,
          "notNull": true
        },
        "oauth_client_id": {
          "name": "oauth_client_id",
          "type": "uuid",
          "primaryKey": false,
          "notNull": true
        },
        "user_id": {
          "name": "user_id",
          "type": "uuid",
          "primaryKey": false,
          "notNull": true
        },
        "redirect_uri": {
          "name": "redirect_uri",
          "type": "text",
          "primaryKey": false,
          "notNull": true
        },
        "code_challenge": {
          "name": "code_challenge",
          "type": "text",
          "primaryKey": false,
          "notNull": true
        },
        "code_challenge_method": {
          "name": "code_challenge_method",
          "type": "code_challenge_method",
          "typeSchema": "public",
          "primaryKey": false,
          "notNull": true,
          "default": "'S256'"
        },
        "nonce": {
          "name": "nonce",
          "type": "varchar(255)",
          "primaryKey": false,
          "notNull": false
        },
        "scopes": {
          "name": "scopes",
          "type": "jsonb",
          "primaryKey": false,
          "notNull": true,
          "default": "'[]'::jsonb"
        },
        "state": {
          "name": "state",
          "type": "varchar(255)",
          "primaryKey": false,
          "notNull": false
        },
        "expires_at": {
          "name": "expires_at",
          "type": "bigint",
          "primaryKey": false,
          "notNull": true
        },
        "used": {
          "name": "used",
          "type": "boolean",
          "primaryKey": false,
          "notNull": true,
          "default": false
        },
        "used_at": {
          "name": "used_at",
          "type": "bigint",
          "primaryKey": false,
          "notNull": false
        },
        "created_at": {
          "name": "created_at",
          "type": "bigint",
          "primaryKey": false,
          "notNull": true,
          "default": "(EXTRACT(EPOCH FROM NOW())::bigint * 1000)"
        }
      },
      "indexes": {
        "idx_authorization_codes_active": {
          "name": "idx_authorization_codes_active",
          "columns": [
            {
              "expression": "code",
              "isExpression": false,
              "asc": true,
              "nulls": "last"
            },
            {
              "expression": "expires_at",
              "isExpression": false,
              "asc": true,
              "nulls": "last"
            }
          ],
          "isUnique": false,
          "where": "\"authorization_codes\".\"used\" = false",
          "concurrently": false,
          "method": "btree",
          "with": {}
        },
        "idx_authorization_codes_expires_at": {
          "name": "idx_authorization_codes_expires_at",
          "columns": [
            {
              "expression": "expires_at",
              "isExpression": false,
              "asc": true,
              "nulls": "last"
            }
          ],
          "isUnique": false,
          "concurrently": false,
          "method": "btree",
          "with": {}
        },
        "idx_authorization_codes_user_id": {
          "name": "idx_authorization_codes_user_id",
          "columns": [
            {
              "expression": "user_id",
              "isExpression": false,
              "asc": true,
              "nulls": "last"
            }
          ],
          "isUnique": false,
          "concurrently": false,
          "method": "btree",
          "with": {}
        },
        "idx_authorization_codes_oauth_client_id": {
          "name": "idx_authorization_codes_oauth_client_id",
          "columns": [
            {
              "expression": "oauth_client_id",
              "isExpression": false,
              "asc": true,
              "nulls": "last"
            }
          ],
          "isUnique": false,
          "concurrently": false,
          "method": "btree",
          "with": {}
        }
      },
      "foreignKeys": {
        "authorization_codes_oauth_client_id_oauth_clients_id_fk": {
          "name": "authorization_codes_oauth_client_id_oauth_clients_id_fk",
          "tableFrom": "authorization_codes",
          "tableTo": "oauth_clients",
          "columnsFrom": ["oauth_client_id"],
          "columnsTo": ["id"],
          "onDelete": "cascade",
          "onUpdate": "no action"
        },
        "authorization_codes_user_id_users_id_fk": {
          "name": "authorization_codes_user_id_users_id_fk",
          "tableFrom": "authorization_codes",
          "tableTo": "users",
          "columnsFrom": ["user_id"],
          "columnsTo": ["id"],
          "onDelete": "cascade",
          "onUpdate": "no action"
        }
      },
      "compositePrimaryKeys": {},
      "uniqueConstraints": {
        "authorization_codes_code_unique": {
          "name": "authorization_codes_code_unique",
          "nullsNotDistinct": false,
          "columns": ["code"]
        }
      },
      "policies": {},
      "checkConstraints": {},
      "isRLSEnabled": false
    },
    "public.email_verification_tokens": {
      "name": "email_verification_tokens",
      "schema": "",
      "columns": {
        "id": {
          "name": "id",
          "type": "uuid",
          "primaryKey": true,
          "notNull": true,
          "default": "uuidv7()"
        },
        "token": {
          "name": "token",
          "type": "varchar(255)",
          "primaryKey": false,
          "notNull": true
        },
        "user_id": {
          "name": "user_id",
          "type": "uuid",
          "primaryKey": false,
          "notNull": true
        },
        "expires_at": {
          "name": "expires_at",
          "type": "bigint",
          "primaryKey": false,
          "notNull": true
        },
        "used": {
          "name": "used",
          "type": "boolean",
          "primaryKey": false,
          "notNull": true,
          "default": false
        },
        "used_at": {
          "name": "used_at",
          "type": "bigint",
          "primaryKey": false,
          "notNull": false
        },
        "created_at": {
          "name": "created_at",
          "type": "bigint",
          "primaryKey": false,
          "notNull": true,
          "default": "(EXTRACT(EPOCH FROM NOW())::bigint * 1000)"
        }
      },
      "indexes": {
        "idx_email_verification_tokens_user_id": {
          "name": "idx_email_verification_tokens_user_id",
          "columns": [
            {
              "expression": "user_id",
              "isExpression": false,
              "asc": true,
              "nulls": "last"
            }
          ],
          "isUnique": false,
          "concurrently": false,
          "method": "btree",
          "with": {}
        },
        "idx_email_verification_tokens_active": {
          "name": "idx_email_verification_tokens_active",
          "columns": [
            {
              "expression": "token",
              "isExpression": false,
              "asc": true,
              "nulls": "last"
            },
            {
              "expression": "expires_at",
              "isExpression": false,
              "asc": true,
              "nulls": "last"
            }
          ],
          "isUnique": false,
          "where": "\"email_verification_tokens\".\"used\" = false",
          "concurrently": false,
          "method": "btree",
          "with": {}
        },
        "idx_email_verification_tokens_expires_at": {
          "name": "idx_email_verification_tokens_expires_at",
          "columns": [
            {
              "expression": "expires_at",
              "isExpression": false,
              "asc": true,
              "nulls": "last"
            }
          ],
          "isUnique": false,
          "concurrently": false,
          "method": "btree",
          "with": {}
        }
      },
      "foreignKeys": {
        "email_verification_tokens_user_id_users_id_fk": {
          "name": "email_verification_tokens_user_id_users_id_fk",
          "tableFrom": "email_verification_tokens",
          "tableTo": "users",
          "columnsFrom": ["user_id"],
          "columnsTo": ["id"],
          "onDelete": "cascade",
          "onUpdate": "no action"
        }
      },
      "compositePrimaryKeys": {},
      "uniqueConstraints": {
        "email_verification_tokens_token_unique": {
          "name": "email_verification_tokens_token_unique",
          "nullsNotDistinct": false,
          "columns": ["token"]
        }
      },
      "policies": {},
      "checkConstraints": {},
      "isRLSEnabled": false
    },
    "public.refresh_tokens": {
      "name": "refresh_tokens",
      "schema": "",
      "columns": {
        "id": {
          "name": "id",
          "type": "uuid",
          "primaryKey": true,
          "notNull": true,
          "default": "uuidv7()"
        },
        "token_hash": {
          "name": "token_hash",
          "type": "text",
          "primaryKey": false,
          "notNull": true
        },
        "user_id": {
          "name": "user_id",
          "type": "uuid",
          "primaryKey": false,
          "notNull": true
        },
        "oauth_client_id": {
          "name": "oauth_client_id",
          "type": "uuid",
          "primaryKey": false,
          "notNull": true
        },
        "scopes": {
          "name": "scopes",
          "type": "jsonb",
          "primaryKey": false,
          "notNull": true,
          "default": "'[]'::jsonb"
        },
        "expires_at": {
          "name": "expires_at",
          "type": "bigint",
          "primaryKey": false,
          "notNull": true
        },
        "revoked": {
          "name": "revoked",
          "type": "boolean",
          "primaryKey": false,
          "notNull": true,
          "default": false
        },
        "revoked_at": {
          "name": "revoked_at",
          "type": "bigint",
          "primaryKey": false,
          "notNull": false
        },
        "revoked_reason": {
          "name": "revoked_reason",
          "type": "varchar(255)",
          "primaryKey": false,
          "notNull": false
        },
        "previous_token_hash": {
          "name": "previous_token_hash",
          "type": "text",
          "primaryKey": false,
          "notNull": false
        },
        "created_at": {
          "name": "created_at",
          "type": "bigint",
          "primaryKey": false,
          "notNull": true,
          "default": "(EXTRACT(EPOCH FROM NOW())::bigint * 1000)"
        },
        "last_used_at": {
          "name": "last_used_at",
          "type": "bigint",
          "primaryKey": false,
          "notNull": false
        }
      },
      "indexes": {
        "idx_refresh_tokens_active": {
          "name": "idx_refresh_tokens_active",
          "columns": [
            {
              "expression": "token_hash",
              "isExpression": false,
              "asc": true,
              "nulls": "last"
            },
            {
              "expression": "expires_at",
              "isExpression": false,
              "asc": true,
              "nulls": "last"
            }
          ],
          "isUnique": false,
          "where": "\"refresh_tokens\".\"revoked\" = false",
          "concurrently": false,
          "method": "btree",
          "with": {}
        },
        "idx_refresh_tokens_expires_at": {
          "name": "idx_refresh_tokens_expires_at",
          "columns": [
            {
              "expression": "expires_at",
              "isExpression": false,
              "asc": true,
              "nulls": "last"
            }
          ],
          "isUnique": false,
          "concurrently": false,
          "method": "btree",
          "with": {}
        },
        "idx_refresh_tokens_user_id": {
          "name": "idx_refresh_tokens_user_id",
          "columns": [
            {
              "expression": "user_id",
              "isExpression": false,
              "asc": true,
              "nulls": "last"
            }
          ],
          "isUnique": false,
          "concurrently": false,
          "method": "btree",
          "with": {}
        },
        "idx_refresh_tokens_oauth_client_id": {
          "name": "idx_refresh_tokens_oauth_client_id",
          "columns": [
            {
              "expression": "oauth_client_id",
              "isExpression": false,
              "asc": true,
              "nulls": "last"
            }
          ],
          "isUnique": false,
          "concurrently": false,
          "method": "btree",
          "with": {}
        },
        "idx_refresh_tokens_user_active": {
          "name": "idx_refresh_tokens_user_active",
          "columns": [
            {
              "expression": "user_id",
              "isExpression": false,
              "asc": true,
              "nulls": "last"
            },
            {
              "expression": "expires_at",
              "isExpression": false,
              "asc": true,
              "nulls": "last"
            }
          ],
          "isUnique": false,
          "where": "\"refresh_tokens\".\"revoked\" = false",
          "concurrently": false,
          "method": "btree",
          "with": {}
        }
      },
      "foreignKeys": {
        "refresh_tokens_user_id_users_id_fk": {
          "name": "refresh_tokens_user_id_users_id_fk",
          "tableFrom": "refresh_tokens",
          "tableTo": "users",
          "columnsFrom": ["user_id"],
          "columnsTo": ["id"],
          "onDelete": "cascade",
          "onUpdate": "no action"
        },
        "refresh_tokens_oauth_client_id_oauth_clients_id_fk": {
          "name": "refresh_tokens_oauth_client_id_oauth_clients_id_fk",
          "tableFrom": "refresh_tokens",
          "tableTo": "oauth_clients",
          "columnsFrom": ["oauth_client_id"],
          "columnsTo": ["id"],
          "onDelete": "cascade",
          "onUpdate": "no action"
        }
      },
      "compositePrimaryKeys": {},
      "uniqueConstraints": {
        "refresh_tokens_token_hash_unique": {
          "name": "refresh_tokens_token_hash_unique",
          "nullsNotDistinct": false,
          "columns": ["token_hash"]
        }
      },
      "policies": {},
      "checkConstraints": {},
      "isRLSEnabled": false
    }
  },
  "enums": {
    "public.audit_event_type": {
      "name": "audit_event_type",
      "schema": "public",
      "values": ["auth", "token", "client", "security", "user", "realm"]
    },
    "public.code_challenge_method": {
      "name": "code_challenge_method",
      "schema": "public",
      "values": ["S256"]
    },
    "public.grant_type": {
      "name": "grant_type",
      "schema": "public",
      "values": ["authorization_code", "refresh_token", "client_credentials"]
    },
    "public.response_type": {
      "name": "response_type",
      "schema": "public",
      "values": ["code"]
    },
    "public.ssl_required": {
      "name": "ssl_required",
      "schema": "public",
      "values": ["none", "external", "all"]
    },
    "public.token_endpoint_auth_method": {
      "name": "token_endpoint_auth_method",
      "schema": "public",
      "values": ["client_secret_post", "client_secret_basic", "private_key_jwt", "none"]
    }
  },
  "schemas": {},
  "sequences": {},
  "roles": {},
  "policies": {},
  "views": {},
  "_meta": {
    "columns": {},
    "schemas": {},
    "tables": {}
  }
}
